[
  {
    "appOld": {
      "status": true,
      "text": "O seu clube de beneficios e descontos exclusivos",
      "logo": "./assets/images/logo-clube.png",
      "familia": "./assets/images/familia.png",
      "buttom": {
        "img": "./assets/images/buttom-app-old.png",
        "url": "https://clubecondor.com"
      }
    },
    "ofertas": {
      "status": true,
      "titulo": "",
      "desktop": "./assets/images/title-desktop.png",
      "mobile": "./assets/images/title-mobile.png",
      "textOfertas": "./assets/images/text-ofertas.png",
      "collection": {
        "menu": "Menus/MenuDepartamentoOfertasLojaCampanha?campanha=355865",
        "ofertas": "Ofertas/LojaProdutosCampanha?campanha=355865",
        "departamento": "Ofertas/LojaProdutosCampanhaDepartamento?campanha=355865"
      },
      "promo": {
        "status": false,
        "titulo": "<span>todos os </span>ovos de páscoa, chocolates, colombas, azeites e bacalhaus",
        "source": [
          "./assets/images/parcelamento.png"
        ]
      },
      "filtro": [
        {
          "value": 1,
          "nome": "Dinheiro de Volta"
        },
        {
          "value": 2,
          "nome": "Clube Condor"
        },
        {
          "value": 3,
          "nome": "Ofertas com Pack"
        },
        {
          "value": 4,
          "nome": "Preço mais baixo"
        }
      ]
    },
    "header": {
      "status": true,
      "background": "./assets/images/bg_header_mobile.png",
      "kv": "./assets/images/kv.png",
      "kv2": "./assets/images/kv-2.png",
      "title": "SÃO MUITAS CHANCES DE GANHAR!"
    },
    "filterIG": {
      "status": true,
      "titulo": "divirta-se com seu paizão usando nossos filtros especias!",
      "source": [
        {
          "link": "https://bit.ly/32JXPqZ",
          "mobile": "./assets/images/filtros/filtro-mobile-1.png",
          "desktop": "./assets/images/filtros/filtro-desktop-1.png"
        },
        {
          "link": "https://bit.ly/3vcihNz",
          "mobile": "./assets/images/filtros/filtro-mobile-2.png",
          "desktop": "./assets/images/filtros/filtro-desktop-2.png"
        },
        {
          "link": "https://bit.ly/3tCEq7n",
          "mobile": "./assets/images/filtros/filtro-mobile-3.png",
          "desktop": "./assets/images/filtros/filtro-desktop-3.png"
        }
      ]
    },
    "menu": {
      "status": true,
      "img": "./assets/images/logo.png",
      "alt": "Rede Condor",
      "url": "https://www.condor.com.br",
      "source": [
        {
          "status": true,
          "url": "#header",
          "name": "Home",
          "external": false
        },
        {
          "status": true,
          "url": "#sorteios",
          "name": "Ganhadores",
          "external": false
        },
        {
          "status": true,
          "url": "#ofertas",
          "name": "Ofertas",
          "external": false
        },
        {
          "status": true,
          "url": "#ddv",
          "name": "Dinheiro de Volta",
          "external": false
        },
        {
          "status": false,
          "url": "#filtro",
          "name": "Filtro Instagram",
          "external": false
        },
        {
          "status": true,
          "url": "#blog",
          "name": "Blog",
          "external": false
        },
        {
          "status": true,
          "url": "/assets/pdf/regulamento.pdf",
          "name": "Regulamento",
          "external": true
        }
      ]
    },
    "footer": {
      "status": true,
      "title": "©Condor 2021. Todos os direitos reservados.",
      "legal": "Poderá participar desta campanha promocional qualquer consumidor, pessoa física, participante do Clube Condor, com cadastro completo, maior de 18 anos, que efetuar uma compra no valor de R$ 50,00 em uma das lojas Condor. Período de inscrição de 23/09/2021 a 04/11/2021. Promoção válida de 23/09/2021 a 08/11/2021 e autorizada pela SECAP/ME n.º XXXXXXXXXX-XXXX. Consulte os seus números da sorte, produtos participantes, certificado de autorização e regulamento aqui.",
      "source": [
        {
          "icon": "fab fa-facebook-f",
          "url": "https://www.facebook.com/RedeCondor/"
        },
        {
          "icon": "fab fa-instagram",
          "url": "https://www.instagram.com/redecondor/"
        },
        {
          "icon": "fab fa-twitter",
          "url": "https://twitter.com/RedeCondor"
        },
        {
          "icon": "fab fa-youtube",
          "url": "https://www.youtube.com/user/redecondor"
        }
      ]
    },
    "blog": {
      "col": 4,
      "cant": 3,
      "urlPost": "https://www.condor.com.br/institucional",
      "buttom": "Ver tudo",
      "status": true,
      "titulo": "Blog",
      "api": "https://teste.condor.com.br/blog/wp-json/wp/v2",
      "tag": 244,
      "link": "https://www.condor.com.br/blog/"
    },
    "quiz": {
      "status": true,
      "titulo": "Quiz",
      "style": {
        "bg": "#EDEDED",
        "color": "#0014B5"
      },
      "quiz": {
        "id": "interactApp603e3101bdff1d0017462df6",
        "link": "https://quiz.tryinteract.com/#/603e3101bdff1d0017462df6?method=iframe&mobile=1"
      }
    },
    "parceiros": {
      "status": true,
      "titulo": "Parceiros",
      "style": {
        "bg": "#fafafa",
        "color": "#0014B5"
      },
      "image": {
        "mobile":  "./assets/images/parceiros_mobile.png",
        "desktop": "./assets/images/parceiros_mobile.png"
      }
    },
    "ddv": {
      "status": true,
      "logo": "./assets/images/logo-ddv.png",
      "selo": "./assets/images/ddv-selo.png",
      "titulo": "OFERTAS IMBATÍVEIS",
      "subtitulo": "E CRÉDITOS PARA A SUA PRÓXIMA COMPRA.",
      "buttom": {
        "url" : "https://www.condor.com.br/dinheiro-de-volta",
        "text": "Clique e aproveite"
      }
    },
    "sorteios": {
      "status": true,
      "titulo": "SORTEIOS",
      "textoLegal": "Resultado da loteria Federal ",
      "url": "https://www.condor.com.br/aniversario",
      "nds": "NÚMEROS DA SORTE",
      "buttom": {
        "titulo": "consultar os meus números",
        "titulo2": "consultar os <br> meus números",
        "url": "https://clubecondor.com"
      },
      "source": [
        {
          "data": "02/10/2021",
          "number": 3344,
          "file": "010921.pdf"
        },
        {
          "data": "06/10/2021",
          "number": 0,
          "file": "080921.pdf"
        },
        {
          "data": "09/10/2021",
          "number": 0,
          "file": "150921.pdf"
        },
        {
          "data": "13/10/2021",
          "number": 0,
          "file": "220921.pdf"
        },
        {
          "data": "16/10/2021",
          "number": 0,
          "file": "290921.pdf"
        },
        {
          "data": "20/10/2021",
          "number": 0,
          "file": "061021.pdf"
        },
        {
          "data": "23/10/2021",
          "number": 0,
          "file": "131021.pdf"
        },
        {
          "data": "27/10/2021",
          "number": 0,
          "file": "201021.pdf"
        },
        {
          "data": "30/10/2021",
          "number": 0,
          "file": "271021.pdf"
        },
        {
          "data": "03/11/2021",
          "number": 0,
          "file": "031121.pdf"
        },
        {
          "data": "06/11/2021",
          "number": 0,
          "file": "101121.pdf"
        }
      ]
    },
    "participar": {
      "status": true,
      "a": "COMO PARTICIPAR",
      "b": "A CADA",
      "c": "R$ ",
      "d": 50,
      "e": ",00",
      "f": "REAIS",
      "g":"EM COMPRAS <br>NO CONDOR",
      "h":"=",
      "i":"1 NÚMERO DA SORTE"
    }
  }
]
